langchain_llm/__init__.py
langchain_llm/_compat.py
langchain_llm/_huggingface.py
langchain_llm/_types.py
langchain_llm/_vllm.py
langchain_llm/adapters/__init__.py
langchain_llm/adapters/model.py
langchain_llm/adapters/patcher.py
langchain_llm/adapters/template.py
langchain_llm/generation/__init__.py
langchain_llm/generation/baichuan.py
langchain_llm/generation/chatglm.py
langchain_llm/generation/qwen.py
langchain_llm/generation/stream.py
langchain_llm/generation/utils.py
langchain_llm/generation/xverse.py
langchain_llm/utils.py
langchain_llm-0.4.15.dist-info/METADATA
langchain_llm-0.4.15.dist-info/WHEEL
langchain_llm-0.4.15.dist-info/RECORD
