Metadata-Version: 2.1
Name: langchain-llm
Version: 0.4.15
Summary: langchain llm wrapper
Author: xusenlin
Author-email: xusenlin@dnect.cn
Requires-Python: >=3.8.1,<4.0
Classifier: Programming Language :: Python :: 3
Classifier: Programming Language :: Python :: 3.9
Classifier: Programming Language :: Python :: 3.10
Classifier: Programming Language :: Python :: 3.11
Classifier: Programming Language :: Python :: 3.12
Requires-Dist: accelerate (>=0.20.3)
Requires-Dist: cpm_kernels (>=1.0.11)
Requires-Dist: einops (>=0.7.0)
Requires-Dist: langchain (>=0.1.0)
Requires-Dist: loguru (>=0.7.0)
Requires-Dist: openai (>=1.6.1)
Requires-Dist: peft (>=0.4.0)
Requires-Dist: sentencepiece (>=0.1.98)
Requires-Dist: tiktoken (>=0.4.0)
Requires-Dist: transformers (>=4.36.0)
Requires-Dist: transformers_stream_generator (>=0.0.4)
